DatasetsSummarizer/__init__.py
DatasetsSummarizer/_comm_api.py
DatasetsSummarizer/_demodata.py
DatasetsSummarizer/_plot_metadata_table.py
DatasetsSummarizer/build/datasetsVis.js
DatasetsSummarizer/data/taxi_full_metadata_and_scatterplot_coordinates.csv
DatasetsSummarizer/data/taxi_metadata_cleaned_cols_only.csv
datasets_summarizer-0.1.2.dist-info/LICENSE
datasets_summarizer-0.1.2.dist-info/METADATA
datasets_summarizer-0.1.2.dist-info/WHEEL
datasets_summarizer-0.1.2.dist-info/top_level.txt
datasets_summarizer-0.1.2.dist-info/RECORD
