Metadata-Version: 2.1
Name: datasets-summarizer
Version: 0.1.2
Summary: Datasets Summary Viewer. Enables the exploration of dataset search results in Jupyter Notebooks
Home-page: https://github.com/soniacq/DatasetsVis
Author: Sonia Castelo
Author-email: s.castelo@nyu.edu
License: UNKNOWN
Platform: UNKNOWN
Classifier: Programming Language :: Python :: 3
Classifier: License :: OSI Approved :: BSD License
Classifier: Operating System :: OS Independent
Requires-Python: >=3.6
Requires-Dist: python-dateutil
Requires-Dist: numpy
Requires-Dist: scipy
Requires-Dist: scikit-learn
Requires-Dist: networkx
Requires-Dist: notebook
Requires-Dist: datamart-profiler (>=0.8)
Requires-Dist: pandas
